{
  "updated": "2026-06-30",
  "news": [
    {
      "date": "06-30",
      "tags": [{"text":"股价","class":"hot"},{"text":"FSD","class":"fsd"},{"text":"Robotaxi","class":"fsd"}],
      "content": "特斯拉股价涨超8%。FSD V14 Lite发布，HW3车辆也能获得超越其他品牌辅助驾驶能力；Cybercab量产版已停满多个城市停车场，网传7月中旬将在休斯顿投入使用；特斯拉车辆工程副总裁透露7月7日将发布关于得州工厂的重大公告。",
      "url": "https://new.qq.com/rain/a/20260630A024Q200"
    },
    {
      "date": "06-30",
      "tags": [{"text":"Q2交付","class":"hot"},{"text":"财报","class":"fsd"}],
      "content": "特斯拉即将公布2026年Q2交付数据，分析师一致预期超40.6万辆，环比增长12%。交付量是衡量特斯拉需求从2025年低谷复苏是否具有可持续性的首次实质性检验。",
      "url": "https://so.html5.qq.com/page/real/search_news?docid=70000021_9736a42dc4945452"
    },
    {
      "date": "06-29",
      "tags": [{"text":"FSD","class":"fsd"},{"text":"全球认可","class":"hot"}],
      "content": "中国车企理想汽车高管在硅谷测试后公开表示，特斯拉FSD是全球唯一的"第一梯队"自动驾驶系统，技术领先地位获竞争对手认可。",
      "url": "https://theelectricviking.com/"
    },
    {
      "date": "06-27",
      "tags": [{"text":"FSD","class":"fsd"},{"text":"订阅制","class":"hot"}],
      "content": "特斯拉全球FSD全面改为订阅制，中国港澳台地区官网显示买断制将于6月30日后下架。香港买断价5.4万港元（约4.68万人民币），下架后转为订阅模式。中国内地尚无明确时间表。",
      "url": "https://so.html5.qq.com/page/real/search_news?docid=70000021_5736a3e2e8553252"
    },
    {
      "date": "06-21",
      "tags": [{"text":"Semi","class":"product"},{"text":"FSD","class":"fsd"}],
      "content": "特斯拉量产版Semi卡车开始搭载FSD进行实际路测。目击车辆在加州和内华达地区出现，车顶安装FSD校准专用地面真实传感器、LiDAR等工程装置，标志自动驾驶能力向重型卡车平台扩展。",
      "url": "https://so.html5.qq.com/page/real/search_news?docid=70000021_9676a37f0ff98752"
    },
    {
      "date": "06-15",
      "tags": [{"text":"AI芯片","class":"fsd"},{"text":"马斯克","class":"hot"}],
      "content": "马斯克透露特斯拉AI6芯片工程评审顺利，团队表现出色，AI6有望创下单块晶圆可用算力新纪录。AI6定下仅九个月紧凑开发周期，预计2028年下半年投产，将大幅提升自动驾驶算力。",
      "url": "https://so.html5.qq.com/page/real/search_news?docid=70000021_6486a2f725576565"
    },
    {
      "date": "06-13",
      "tags": [{"text":"FSD","class":"fsd"},{"text":"OTA","class":"product"}],
      "content": "特斯拉推送FSD v14.3.4（2026.14.6.10），将FSD、Robotaxi及智能召唤的模型统一，Cybertruck解锁真智能召唤功能，最高时速提升至13km/h。底层AI编译器和运行时用MLIR从零重写。",
      "url": "https://so.html5.qq.com/page/real/search_news?docid=70000021_8326a2b55f267352"
    },
    {
      "date": "06-06",
      "tags": [{"text":"中国","class":"china"},{"text":"交付","class":"hot"}],
      "content": "特斯拉上海超级工厂5月交付超8.5万辆，创2026年单月交付新高，同比增长39.4%，环比增长8%。上海工厂作为全球最大出口中心，交付量占全球总交付量一半以上。同日特斯拉在英国迎来第30万辆交付里程碑。",
      "url": "https://new.qq.com/rain/a/20260606A02BV900"
    }
  ]
}
