{
  "updated": "2026-07-21",
  "news": [
    {
      "date": "07-21",
      "tags": [
        {
          "text": "公益拍卖",
          "class": "hot"
        },
        {
          "text": "广州中南",
          "class": "hot"
        }
      ],
      "content": "广州中南拍卖7月21-23日举槌23把紫砂壶公益专场：顾景舟/蒋蓉款4把、朱可心/汪寅仙款5把、周桂珍/季益顺/鲍志强款3把、裴石民/吕尧臣/徐汉棠款4把、王石耕/何道洪/高建芳/吴运根款4把、施小马/李松亭款3把，所得款项部分捐赠公益。",
      "sources": [
        "广州中南拍卖",
        "潇湘晨报公告"
      ],
      "url": "http://gonggao.xfrb.com.cn/details.html?id=145072"
    },
    {
      "date": "07-13",
      "tags": [
        {
          "text": "市场真相",
          "class": "hot"
        },
        {
          "text": "造假",
          "class": "hot"
        }
      ],
      "content": "紫砂壶2026年最残酷真相：拍场与直播间两个世界。同一把顾景舟相明石瓢壶：2010嘉德1232万、2015匡时2702.5万、2026中贸圣佳1535.25万。造假4类曝光：新壶做旧、化工壶钴超标60%、灌浆手拉壶失去紫砂灵魂、直播间1980元低劣壶充斥市场。",
      "sources": [
        "今日头条",
        "雅昌艺术网",
        "中贸圣佳"
      ],
      "url": "https://www.toutiao.com/article/7661889887699829282"
    },
    {
      "date": "07-12",
      "tags": [
        {
          "text": "西泠春拍",
          "class": "hot"
        },
        {
          "text": "落槌价",
          "class": "hot"
        }
      ],
      "content": "西泠印社2026春拍紫砂专场完整落槌价出炉：全场最高何道洪制紫泥新竹桃园壶落槌290万元（含佣成交价333.5万元）；清中期杨彭年制陈曼生铭紫泥调砂合欢壶落槌240万元；清乾隆继玩款朱泥德钟壶落槌125万元。清早期吴元苹制朱泥莲子壶落槌28万元。",
      "sources": [
        "纯色紫砂",
        "网易",
        "紫砂中华"
      ],
      "url": "https://www.163.com/dy/article/L1KSTBRD052584M6.html"
    },
    {
      "date": "07-11",
      "tags": [
        {
          "text": "西泠春拍",
          "class": "hot"
        },
        {
          "text": "成交结果",
          "class": "hot"
        }
      ],
      "content": "西泠春拍紫砂专场成交结果出炉：全场最高何道洪制紫泥新竹桃园壶以333.5万元成交登顶，202件历代紫砂器物与茶文物顺利拍出。本场系今夏紫砂收藏市场最重要风向标。",
      "sources": [
        "紫砂中华",
        "雅昌艺术网",
        "网易"
      ],
      "url": "https://www.163.com/dy/article/L1JAP8N40514EFHI.html"
    },
    {
      "date": "07-08",
      "tags": [
        {
          "text": "西泠预展",
          "class": "hot"
        },
        {
          "text": "茶文化",
          "class": "default"
        }
      ],
      "content": "2026西泠印社春季拍卖会预展于7月8日在杭州国际会议中心洲际酒店盛大启幕，涵盖中国历代紫砂器物暨茶文化等专场，正式拍卖于7月11-13日举槌。",
      "sources": [
        "雅昌艺术网",
        "西泠印社"
      ],
      "url": "https://news.artron.net/20260708/n1152122.html"
    },
    {
      "date": "07-05",
      "tags": [
        {
          "text": "上海嘉禾",
          "class": "hot"
        },
        {
          "text": "春拍",
          "class": "default"
        }
      ],
      "content": "上海嘉禾2026春拍唐伯琴《蜂菊壶》十件套（本山老段泥，容量380CC）估价8-10万元。作品承袭家族筋囊古法，菊瓣规整、蜂钮灵动，紫砂文脉与自然意趣相融。",
      "sources": [
        "雅昌艺术网",
        "上海嘉禾"
      ],
      "url": "https://m-news.artron.net/20260630/n1151879.html"
    },
    {
      "date": "07-03",
      "tags": [
        {
          "text": "中贸圣佳",
          "class": "hot"
        },
        {
          "text": "春拍",
          "class": "default"
        }
      ],
      "content": "中贸圣佳2026春拍紫砂专场亮点：唐云旧藏明末清初陈共之答欢提梁壶以270万元落槌；顾景舟制吴湖帆书画相明石瓢壶以1535.25万元成交，创紫砂专场最高价。集制壶名手、文人书画、名家篆刻于一体。",
      "sources": [
        "淘壶人",
        "中贸圣佳",
        "雅昌艺术网"
      ],
      "url": "https://www.toutiao.com/article/7658204384568115746"
    }
  ]
}